argosim/__init__.py
argosim/antenna_utils.py
argosim/beam_utils.py
argosim/clean.py
argosim/data_utils.py
argosim/imaging_utils.py
argosim/metrics_utils.py
argosim/plot_utils.py
argosim/rand_utils.py
argosim/tests/test_antenna_utils.py
argosim/tests/test_beam_utils.py
argosim/tests/test_clean.py
argosim/tests/test_data_utils.py
argosim/tests/test_imaging_utils.py
argosim/tests/test_metrics_utils.py
argosim/tests/test_plot_utils.py
argosim/tests/test_rand_utils.py
argosim-1.0.1.dist-info/licenses/LICENSE
argosim-1.0.1.dist-info/METADATA
argosim-1.0.1.dist-info/WHEEL
argosim-1.0.1.dist-info/top_level.txt
argosim-1.0.1.dist-info/RECORD
