Metadata-Version: 2.4
Name: argosim
Version: 1.0.1
Summary: Radio interferometric simulations package for the ARGOS radio telescope.
Author-email: Ezequiel Centofanti <ezequiel.centofanti@cea.fr>, Emma Ayçoberry <Emma.AYCOBERRY@cea.fr>
Maintainer-email: Ezequiel Centofanti <ezequiel.centofanti@cea.fr>, Emma Ayçoberry <Emma.AYCOBERRY@cea.fr>
Requires-Python: >=3.11
License-File: LICENSE
Requires-Dist: numpy>=1.26
Requires-Dist: matplotlib>=3.8
Requires-Dist: scikit-image>=0.22
Requires-Dist: jax>=0.4
Provides-Extra: doc
Requires-Dist: myst-parser; extra == "doc"
Requires-Dist: numpydoc; extra == "doc"
Requires-Dist: sphinx; extra == "doc"
Requires-Dist: sphinx-book-theme; extra == "doc"
Provides-Extra: lint
Requires-Dist: black; extra == "lint"
Requires-Dist: isort; extra == "lint"
Provides-Extra: release
Requires-Dist: build; extra == "release"
Requires-Dist: twine; extra == "release"
Provides-Extra: test
Requires-Dist: pytest; extra == "test"
Requires-Dist: pytest-cov; extra == "test"
Requires-Dist: pytest-pydocstyle; extra == "test"
Provides-Extra: gui
Requires-Dist: pyQt6; extra == "gui"
Provides-Extra: dev
Requires-Dist: argosim[doc,gui,lint,release,test]; extra == "dev"
Dynamic: license-file
